{"current":[{"event":1,"points":61,"total_points":61,"rank":2607688,"rank_sort":2632753,"overall_rank":2607687,"percentile_rank":30,"bank":0,"value":1000,"event_transfers":0,"event_transfers_cost":0,"points_on_bench":0},{"event":2,"points":47,"total_points":108,"rank":6465899,"rank_sort":6479767,"overall_rank":3840714,"percentile_rank":65,"bank":0,"value":1000,"event_transfers":0,"event_transfers_cost":0,"points_on_bench":11},{"event":3,"points":40,"total_points":148,"rank":8554323,"rank_sort":8561579,"overall_rank":5244406,"percentile_rank":80,"bank":2,"value":1001,"event_transfers":2,"event_transfers_cost":0,"points_on_bench":16},{"event":4,"points":58,"total_points":206,"rank":7782166,"rank_sort":7789870,"overall_rank":5782174,"percentile_rank":70,"bank":6,"value":1002,"event_transfers":1,"event_transfers_cost":0,"points_on_bench":12},{"event":5,"points":34,"total_points":240,"rank":9319689,"rank_sort":9331100,"overall_rank":6566427,"percentile_rank":80,"bank":0,"value":1005,"event_transfers":0,"event_transfers_cost":0,"points_on_bench":21},{"event":6,"points":84,"total_points":324,"rank":134960,"rank_sort":135699,"overall_rank":2831890,"percentile_rank":5,"bank":0,"value":1005,"event_transfers":0,"event_transfers_cost":0,"points_on_bench":13},{"event":7,"points":77,"total_points":401,"rank":1816046,"rank_sort":1820353,"overall_rank":2144109,"percentile_rank":20,"bank":5,"value":1009,"event_transfers":2,"event_transfers_cost":0,"points_on_bench":6},{"event":8,"points":0,"total_points":401,"rank":null,"rank_sort":null,"overall_rank":2144109,"percentile_rank":null,"bank":5,"value":1016,"event_transfers":0,"event_transfers_cost":0,"points_on_bench":0}],"past":[{"season_name":"2017/18","total_points":1710,"rank":3495387},{"season_name":"2018/19","total_points":1891,"rank":3189948},{"season_name":"2019/20","total_points":1986,"rank":2057842},{"season_name":"2020/21","total_points":1786,"rank":4610422},{"season_name":"2021/22","total_points":2193,"rank":1241877},{"season_name":"2022/23","total_points":2381,"rank":787624},{"season_name":"2023/24","total_points":2248,"rank":1583494},{"season_name":"2024/25","total_points":2420,"rank":446849}],"chips":[{"name":"bboost","time":"2025-08-15T10:48:01.063839Z","event":1},{"name":"wildcard","time":"2025-09-15T05:21:37.692784Z","event":5},{"name":"3xc","time":"2025-09-20T17:00:58.057040Z","event":6}]}